fastapi_vite_dara/__init__.py
fastapi_vite_dara/config.py
fastapi_vite_dara/loader.py
fastapi_vite_dara/runner.py
fastapi_vite_dara/templates/index.html
fastapi_vite_dara-0.4.0.dist-info/METADATA
fastapi_vite_dara-0.4.0.dist-info/WHEEL
fastapi_vite_dara-0.4.0.dist-info/RECORD
