Metadata-Version: 2.1
Name: fastapi_vite_dara
Version: 0.4.0
Summary: Fork of fastapi-vite to support wider range of jinja2 version.
Home-page: https://github.com/causalens/fastapi-vite
License: MIT
Keywords: fastapi,starlette,vite,dara
Author: causaLens
Author-email: support@causalens.com
Requires-Python: >=3.8,<4
Classifier: Framework :: AsyncIO
Classifier: Intended Audience :: Developers
Classifier: License :: OSI Approved :: MIT License
Classifier: Programming Language :: Python :: 3
Classifier: Programming Language :: Python :: 3.8
Classifier: Programming Language :: Python :: 3.9
Classifier: Programming Language :: Python :: 3.10
Classifier: Programming Language :: Python :: 3.11
Classifier: Programming Language :: Python :: 3.12
Classifier: Programming Language :: Python :: 3.13
Classifier: Programming Language :: Python :: 3 :: Only
Requires-Dist: Jinja2
Requires-Dist: fastapi (>=0.100.0)
Requires-Dist: pydantic (>=1.10.17,<3.0.0)
Project-URL: Repository, https://github.com/causalens/fastapi-vite
